norm/__init__.py
norm/config.py
norm/engine.py
norm/security.py
norm/utils.py
norm/.idea/misc.xml
norm/.idea/modules.xml
norm/.idea/norm.iml
norm/.idea/vcs.xml
norm/.idea/workspace.xml
norm/__pycache__/__init__.cpython-36.pyc
norm/__pycache__/__init__.cpython-37.pyc
norm/__pycache__/config.cpython-36.pyc
norm/__pycache__/config.cpython-37.pyc
norm/__pycache__/engine.cpython-36.pyc
norm/__pycache__/engine.cpython-37.pyc
norm/__pycache__/security.cpython-36.pyc
norm/__pycache__/security.cpython-37.pyc
norm/__pycache__/utils.cpython-36.pyc
norm/__pycache__/utils.cpython-37.pyc
norm/db/norm.db
norm/executable/__init__.py
norm/executable/command.py
norm/executable/constant.py
norm/executable/__pycache__/__init__.cpython-36.pyc
norm/executable/__pycache__/__init__.cpython-37.pyc
norm/executable/__pycache__/command.cpython-36.pyc
norm/executable/__pycache__/command.cpython-37.pyc
norm/executable/__pycache__/constant.cpython-36.pyc
norm/executable/__pycache__/constant.cpython-37.pyc
norm/executable/expression/__init__.py
norm/executable/expression/argument.py
norm/executable/expression/arithmetic.py
norm/executable/expression/assignment.py
norm/executable/expression/code.py
norm/executable/expression/condition.py
norm/executable/expression/evaluation.py
norm/executable/expression/query.py
norm/executable/expression/slice.py
norm/executable/expression/__pycache__/__init__.cpython-36.pyc
norm/executable/expression/__pycache__/__init__.cpython-37.pyc
norm/executable/expression/__pycache__/argument.cpython-36.pyc
norm/executable/expression/__pycache__/argument.cpython-37.pyc
norm/executable/expression/__pycache__/arithmetic.cpython-36.pyc
norm/executable/expression/__pycache__/arithmetic.cpython-37.pyc
norm/executable/expression/__pycache__/assignment.cpython-36.pyc
norm/executable/expression/__pycache__/code.cpython-36.pyc
norm/executable/expression/__pycache__/condition.cpython-36.pyc
norm/executable/expression/__pycache__/condition.cpython-37.pyc
pynorm-0.1.12.dist-info/LICENSE.txt
pynorm-0.1.12.dist-info/METADATA
pynorm-0.1.12.dist-info/WHEEL
pynorm-0.1.12.dist-info/top_level.txt
pynorm-0.1.12.dist-info/RECORD
