Metadata-Version: 2.1
Name: pynorm
Version: 0.1.12
Summary: A probabilistic logic programming library for data science
Home-page: https://github.com/reasoned-ai/norm
Author: Xu Miao
Author-email: xu@reasoned.ai
License: Apache 2.0
Platform: UNKNOWN
Classifier: License :: OSI Approved :: Apache Software License
Classifier: Programming Language :: Python
Classifier: Programming Language :: Python :: 3
Classifier: Programming Language :: Python :: 3.6
Classifier: Programming Language :: Python :: Implementation :: CPython
Requires-Python: >=3.6.0
Requires-Dist: IPython (~=5.5.0)
Requires-Dist: hashids
Requires-Dist: alembic
Requires-Dist: antlr4-python3-runtime
Requires-Dist: babel
Requires-Dist: bqplot
Requires-Dist: cython
Requires-Dist: dask
Requires-Dist: docutils
Requires-Dist: fastparquet
Requires-Dist: gcloud
Requires-Dist: h5py
Requires-Dist: humanize
Requires-Dist: ipywidgets
Requires-Dist: jedi
Requires-Dist: Keras
Requires-Dist: locket
Requires-Dist: Mako
Requires-Dist: Markdown
Requires-Dist: matplotlib
Requires-Dist: mock
Requires-Dist: msgpack
Requires-Dist: numpy
Requires-Dist: numpydoc
Requires-Dist: packaging
Requires-Dist: pandas
Requires-Dist: parsedatetime
Requires-Dist: pep8
Requires-Dist: PyYAML
Requires-Dist: requests (~=2.21.0)
Requires-Dist: scikit-image
Requires-Dist: scikit-learn
Requires-Dist: scipy
Requires-Dist: sortedcollections
Requires-Dist: sortedcontainers
Requires-Dist: Sphinx
Requires-Dist: sphinx-rtd-theme
Requires-Dist: scrubadub
Requires-Dist: SQLAlchemy
Requires-Dist: SQLAlchemy-Utils
Requires-Dist: toolz
Requires-Dist: tox
Requires-Dist: xgboost
